{
    "Cerro Negro": {
        "topLeftLat": 22,
        "topLeftLng": -96,
        "bottomRightLat": 2,
        "bottomRightLng": -76,
        "volcanoLat": 12.5078,
        "volcanoLng": -86.7022,
        "minZoom": 6,
        "maxZoom": 10,
        "initialZoom": 8
    },
    "Cerro Negro (markers)": {
        "topLeftLat": 22,
        "topLeftLng": -96,
        "bottomRightLat": 2,
        "bottomRightLng": -76,
        "volcanoLat": 12.5078,
        "volcanoLng": -86.7022,
        "minZoom": 6,
        "maxZoom": 10,
        "initialZoom": 8,
        "extraMarkers": [
            {
                "x": 12.1150,
                "y": -86.2362,
                "name": "Managua, Nicaragua"
            },{
                "x": 11.1292,
                "y": -84.7772,
                "name": "San Carlos, Nicaragua"
            }
        ]
    },
    "Mt. St. Helens": {
        "topLeftLat": 56,
        "topLeftLng": -130,
        "bottomRightLat": 36,
        "bottomRightLng": -110,
        "volcanoLat": 46.1914,
        "volcanoLng": -122.1956,
        "minZoom": 6,
        "maxZoom": 10,
        "initialZoom": 8
    },
    "Everything": {
        "topLeftLat": 180,
        "topLeftLng": -180,
        "bottomRightLat": -180,
        "bottomRightLng": 180,
        "volcanoLat": 36,
        "volcanoLng": -120,
        "minZoom": 0,
        "maxZoom": 10000,
        "initialZoom": 8
    },
    "Mount Pinatubo": {
        "topLeftLat": 25,
        "topLeftLng": 130,
        "bottomRightLat": 5,
        "bottomRightLng": 110,
        "volcanoLat": 15.1429,
        "volcanoLng": 120.3496,
        "minZoom": 6,
        "maxZoom": 10,
        "initialZoom": 8
    },
    "Volcan de Fuego": {
        "topLeftLat": 4,
        "topLeftLng": -100,
        "bottomRightLat": 25,
        "bottomRightLng": -80,
        "volcanoLat": 14.4747,
        "volcanoLng": -90.8806,
        "minZoom": 6,
        "maxZoom": 10,
        "initialZoom": 8
    },
    "Mount Ruapehu": {
        "topLeftLat": -49,
        "topLeftLng": 165,
        "bottomRightLat": -29,
        "bottomRightLng": 185,
        "volcanoLat": -39.2817,
        "volcanoLng": 175.5685,
        "minZoom": 6,
        "maxZoom": 10,
        "initialZoom": 8
    },
    "Mount Fuji": {
        "topLeftLat": 25,
        "topLeftLng": 128,
        "bottomRightLat": 45,
        "bottomRightLng": 148,
        "volcanoLat": 35.3606,
        "volcanoLng": 138.7274,
        "minZoom": 6,
        "maxZoom": 10,
        "initialZoom": 8
    },
    "Mount Vesuvius": {
        "topLeftLat": 30,
        "topLeftLng": 4,
        "bottomRightLat": 50,
        "bottomRightLng": 24,
        "volcanoLat": 40.8224,
        "volcanoLng": 14.4289,
        "minZoom": 6,
        "maxZoom": 10,
        "initialZoom": 8
    },
    "Seismic CA": {
        "topLeftLat": 41.993157,
        "topLeftLng": -124.542844,
        "bottomRightLat": 32.735104,
        "bottomRightLng": -114.470318,
        "minZoom": 6,
        "maxZoom": 12,
        "initialZoom": 6
    }
}